<?xml version="1.0" encoding="utf-8" ?>
<odoo>
    <record id="hr_contract_view_form" model="ir.ui.view">
        <field name="name">hr.contract.view.form.payroll</field>
        <field name="model">hr.contract</field>
        <field name="inherit_id" ref="hr_contract.hr_contract_view_form" />
        <field name="arch" type="xml">
            <xpath expr="//group[@name='salary_and_advantages']" position="inside">
                <field name="struct_id" required="1" />
                <field name="company_id" groups="base.group_multi_company" />
                <field name="currency_id" invisible="1" />
            </xpath>
            <xpath expr="//field[@name='wage']" position="after">
                <field name="schedule_pay" />
            </xpath>
            <xpath expr="//group[@name='main_info']" position="inside">
                <separator string="Contract Advantages" />
                <field name="hr_contract_advantage_ids">
                    <tree editable="bottom">
                        <field
                            name="advantage_template_id"
                            options="{'no_quick_create':True,'no_create_edit':True,'no_open': True,}"
                        />
                        <field name="advantage_template_code" />
                        <field name="advantage_lower_bound" />
                        <field name="advantage_upper_bound" />
                        <field name="amount" />
                    </tree>
                </field>
            </xpath>
        </field>
    </record>
</odoo>
